{
  "generated_at": "2026-04-30T09:23:54Z",
  "items": [
    {
      "source": "a16z News",
      "type": "website",
      "title": "Call the Plumber; We’ve Got a Leaky Abstraction",
      "published_at": "Wed, 29 Apr 2026 14:02:41 GMT",
      "link": "https://www.a16z.news/p/call-the-plumber-weve-got-a-leaky",
      "summary": "A model of how things break, for non-doomers"
    },
    {
      "source": "TechCrunch Startups",
      "type": "website",
      "title": "Parallel Web Systems hits $2B valuation five months after its last big raise",
      "published_at": "Wed, 29 Apr 2026 18:33:05 +0000",
      "link": "https://techcrunch.com/2026/04/29/parallel-web-systems-hits-2b-valuation-five-months-after-its-last-big-raise/",
      "summary": "The AI agent-tool startup founded by former Twitter CEO Parag Agrawal has raised $100 million, led by Sequoia, months after raising a previous $100 million."
    },
    {
      "source": "VC News Daily",
      "type": "website",
      "title": "Liquid Instruments Nabs $50M Series C",
      "published_at": "29 Apr 2026 17:44:11 CDT",
      "link": "https://vcnewsdaily.com/liquid-instruments/venture-capital-funding/gmyfsvxbxh",
      "summary": "SAN DIEGO, CA, Liquid Instruments, a pioneer in software-defined test solutions, today announced the close of its $50 million Series C funding round."
    },
    {
      "source": "YC Launches",
      "type": "website",
      "title": "YC Launches",
      "published_at": "",
      "link": "https://www.ycombinator.com/launches",
      "summary": ""
    },
    {
      "source": "Product Hunt",
      "type": "website",
      "title": "Hera Launch",
      "published_at": "2026-04-27T02:33:59-07:00",
      "link": "https://www.producthunt.com/products/hera-6",
      "summary": "Create studio-quality launch videos with AI Discussion | Link"
    },
    {
      "source": "Sequoia Stories",
      "type": "website",
      "title": "Partnering with Ineffable Intelligence: A Superlearner for the Era of Experience",
      "published_at": "Mon, 27 Apr 2026 14:15:11 +0000",
      "link": "https://sequoiacap.com/article/partnering-with-ineffable-intelligence-a-superlearner-for-the-era-of-experience/",
      "summary": "The post Partnering with Ineffable Intelligence: A Superlearner for the Era of Experience appeared first on Sequoia Capital ."
    },
    {
      "source": "a16z",
      "type": "youtube",
      "title": "Box CEO on AI Agents & Why Enterprise Can't Keep Up | a16z",
      "published_at": "",
      "link": "https://www.youtube.com/watch?v=dvVbA9OcBqs",
      "summary": ""
    },
    {
      "source": "Sequoia Capital",
      "type": "youtube",
      "title": "Andrej Karpathy: From Vibe Coding to Agentic Engineering",
      "published_at": "",
      "link": "https://www.youtube.com/watch?v=96jN2OCOfLs",
      "summary": ""
    },
    {
      "source": "Silicon Valley Girl",
      "type": "youtube",
      "title": "Double Your Income With AI in 3 Months (Here's the Stack)",
      "published_at": "",
      "link": "https://www.youtube.com/watch?v=zL2PIa72gJ4",
      "summary": ""
    },
    {
      "source": "20VC",
      "type": "youtube",
      "title": "AppLovin CEO: Why Founders Shouldn't Angel Invest & Why the Best Don't Need Mentorship",
      "published_at": "",
      "link": "https://www.youtube.com/watch?v=dlPCz8Jwypw",
      "summary": ""
    },
    {
      "source": "Latent Space",
      "type": "youtube",
      "title": "Android Moment for Vehicles: 50 OSes, OTA, safety-critical AI — Qasar & Peter, Applied Intuition",
      "published_at": "",
      "link": "https://www.youtube.com/watch?v=rv23_KcHt4s",
      "summary": ""
    },
    {
      "source": "Lenny's Podcast",
      "type": "youtube",
      "title": "How to win when software is not a moat | Evan Spiegel (Snapchat CEO)",
      "published_at": "",
      "link": "https://www.youtube.com/watch?v=-7Yol5vX5xw",
      "summary": ""
    },
    {
      "source": "YC Official",
      "type": "youtube",
      "title": "Demis Hassabis: Agents, AGI & The Next Big Scientific Breakthrough",
      "published_at": "",
      "link": "https://www.youtube.com/watch?v=JNyuX1zoOgU",
      "summary": ""
    }
  ]
}